README.md
setup.py
tytycss/__init__.py
tytycss/tytycss.py
tytycss.egg-info/PKG-INFO
tytycss.egg-info/SOURCES.txt
tytycss.egg-info/dependency_links.txt
tytycss.egg-info/entry_points.txt
tytycss.egg-info/top_level.txt
tytycss/bin/__init__.py
tytycss/bin/beau.py