Metadata-Version: 1.1
Name: tytycss
Version: 0.7
Summary: search css file by selector-string/prelude-string
Home-page: https://github.com/ihgazni2/tytycss
Author: dapeli
Author-email: terryinzaghi@163.com
License: MIT
Platform: UNKNOWN
Classifier: Environment :: Console
Classifier: Environment :: Web Environment
Classifier: Intended Audience :: End Users/Desktop
Classifier: Intended Audience :: Developers
Classifier: Intended Audience :: System Administrators
Classifier: Programming Language :: Python
